{
   "schemaVersion": 1,
   "id": "gfx-debuggers",
   "version": "${version}",
   "name": "gfx-debuggers",
   "description": "Helps you inject graphics debuggers (NSight and Renderdoc) into Minecraft, without fiddling with launchers or JVM arguments.",
   "authors": ["xirreal"],
   "contact": {
      "sources": "https://github.com/xirreal/gfx-debuggers"
   },
   "license": "MIT",
   "icon": "assets/gfx-debuggers/icon.png",
   "environment": "*",
   "entrypoints": {
      "preLaunch": ["dev.xirreal.GfxDebuggers"]
   },
   "depends": {
      "fabricloader": ">=0.10.7",
      "minecraft": "*",
      "java": ">=17"
   }
}
